Metadata-Version: 2.0
Name: QGDT
Version: 0.3.0
Summary: Question Generation Algorithm Based on Depth Learning and Template,QGDT
Home-page: https://github.com/pzs741/QGDT
Author: Ex_treme
Author-email: pzsyjsgldd@163.com
License: MIT
Platform: UNKNOWN
Classifier: Programming Language :: Python :: 3
Classifier: Natural Language :: English
Classifier: Intended Audience :: Developers
Requires-Dist: TEDT (==0.5)
Requires-Dist: gensim (==3.4.0)
Requires-Dist: jieba (==0.39)
Requires-Dist: numpy (==1.14.2)
Requires-Dist: pandas (==0.22.0)
Requires-Dist: pytorch-cpu (==0.4.0)
Requires-Dist: scikit-learn (==0.19.1)
